nutrient_calculator-1.2.0.dist-info/METADATA
nutrient_calculator-1.2.0.dist-info/WHEEL
nutrient_calculator/__init__.py
nutrient_calculator/nutrient_calculator.cpython-39-x86_64-linux-gnu.so
nutrient_calculator-1.2.0.dist-info/RECORD
