Metadata-Version: 2.3
Name: nutrient_calculator
Version: 1.2.0
